LICENSE
MANIFEST.in
README.rst
setup.py
wificamera/__init__.py
wificamera/wificamera.py
wificamera.egg-info/PKG-INFO
wificamera.egg-info/SOURCES.txt
wificamera.egg-info/dependency_links.txt
wificamera.egg-info/top_level.txt