Metadata-Version: 1.0
Name: wificamera
Version: 0.1.1
Summary: WifiCamera is a Python module for controlling the network camera CS-W07G-CY.
Home-page: https://github.com/lanius/wificamera/
Author: lanius
Author-email: lanius@nirvake.org
License: MIT
Platform: UNKNOWN
Classifier: Development Status :: 4 - Beta
Classifier: Intended Audience :: Developers
Classifier: License :: OSI Approved :: MIT License
Classifier: Operating System :: OS Independent
Classifier: Programming Language :: Python
Classifier: Topic :: Multimedia :: Graphics :: Capture
Classifier: Topic :: Software Development :: Libraries :: Python Modules
